optilife_models/__init__.py
optilife_models/bill_service/__init__.py
optilife_models/bill_service/v1/__init__.py
optilife_models/bill_service/v1/bill_service/v1/parsed_bill_pb2.py
optilife_models/bill_service/v1/bill_service/v1/request_pb2.py
optilife_models-2025.6.26.1536.dist-info/METADATA
optilife_models-2025.6.26.1536.dist-info/WHEEL
optilife_models-2025.6.26.1536.dist-info/top_level.txt
optilife_models-2025.6.26.1536.dist-info/RECORD
