Metadata-Version: 2.4
Name: optilife-models
Version: 2025.6.26.1536
Summary: Generated Protobuf models for My Project
Author-email: Your Name <your@email.com>
Classifier: Programming Language :: Python :: 3
Classifier: License :: OSI Approved :: MIT License
Classifier: Operating System :: OS Independent
Requires-Python: >=3.13
Requires-Dist: protobuf>=4.21.0
Requires-Dist: setuptools>=80.9.0
Requires-Dist: wheel>=0.45.1
